{"skeleton":{"hash":"mUeUYDpb6zo","spine":"3.8-from-4.0-from-4.1-from-4.2.40","x":-343.58,"y":-554.4,"width":777.42,"height":1143.27,"images":"../PubG_Assets/","audio":"./audio"},"bones":[{"name":"root"}],"slots":[{"name":"run1","bone":"root","attachment":"run1"},{"name":"run2","bone":"root","attachment":"run2"},{"name":"run 3","bone":"root","attachment":"run 3"},{"name":"run4","bone":"root","attachment":"run4"},{"name":"Run5","bone":"root","attachment":"Run5"}],"skins":[{"name":"default","attachments":{"run1":{"run1":{"x":-36.11,"y":-5.41,"width":607,"height":1080}},"run2":{"run2":{"x":-35.08,"y":0.5,"width":607,"height":1080}},"run 3":{"run 3":{"x":-40.08,"y":-14.4,"width":607,"height":1080}},"run4":{"run4":{"x":130.34,"y":41.08,"width":607,"height":1080}},"Run5":{"Run5":{"x":92.94,"y":48.87,"width":607,"height":1080}}}}],"animations":{"animation":{"slots":{"run1":{"color":[{"time":0.3,"color":"ffffffff"},{"time":0.3333,"color":"ffffff00"}]},"run2":{"color":[{"color":"ffffff00","curve":"stepped"},{"time":0.3,"color":"ffffff00"},{"time":0.3333,"color":"ffffffff","curve":"stepped"},{"time":0.6333,"color":"ffffffff"},{"time":0.6667,"color":"ffffff00"}]},"run 3":{"color":[{"color":"ffffff00","curve":"stepped"},{"time":0.6333,"color":"ffffff00"},{"time":0.6667,"color":"ffffffff"}]},"run4":{"color":[{"color":"ffffff00","curve":"stepped"},{"time":0.9667,"color":"ffffff00"}]}}},"spin":{"slots":{"run1":{"color":[{"color":"ffffff00","curve":"stepped"},{"time":0.4667,"color":"ffffff00"},{"time":0.5,"color":"ffffffff","curve":"stepped"},{"time":0.8,"color":"ffffffff"},{"time":0.8333,"color":"ffffff00"}]},"run2":{"color":[{"color":"ffffff00","curve":"stepped"},{"time":0.2,"color":"ffffff00"},{"time":0.2333,"color":"ffffffff","curve":"stepped"},{"time":0.4667,"color":"ffffffff"},{"time":0.5,"color":"ffffff00"}]},"run 3":{"color":[{"time":0.2,"color":"ffffffff"},{"time":0.2333,"color":"ffffff00"}]},"run4":{"color":[{"color":"ffffff00"}]},"Run5":{"color":[{"color":"ffffff00","curve":"stepped"},{"time":0.8,"color":"ffffff00"},{"time":0.8333,"color":"ffffffff","curve":"stepped"},{"time":1.2,"color":"ffffffff"}]}}}}}